{
    "a4": [
        [
            "v11",
            0,
            18.054404688530248
        ],
        [
            [
                "v11",
                "v9"
            ],
            18.054405
        ],
        [
            "v9",
            19.15474212969113,
            33.877592612413125
        ],
        [
            [
                "v9",
                "v20"
            ],
            33.877593
        ],
        [
            [
                "v20",
                "v10"
            ],
            36.419683
        ],
        [
            "v10",
            39.240744974531964,
            59.616846524094385
        ],
        [
            [
                "v10",
                "v7"
            ],
            59.616847
        ],
        [
            [
                "v7",
                "v2"
            ],
            60.386411
        ],
        [
            "v2",
            63.47548395889164,
            69.1902355221704
        ],
        [
            [
                "v2",
                "v3"
            ],
            69.190236
        ],
        [
            [
                "v3",
                "v8"
            ],
            75.73561
        ],
        [
            "v8",
            76.07438123140038,
            80.01556074424681
        ],
        [
            [
                "v8",
                "v16"
            ],
            80.015561
        ],
        [
            "v16",
            83.12243967585165,
            88.8476897617864
        ],
        [
            [
                "v16",
                "v8"
            ],
            88.84769
        ],
        [
            [
                "v8",
                "v18"
            ],
            91.954569
        ],
        [
            [
                "v18",
                "v8"
            ],
            94.185891
        ],
        [
            [
                "v8",
                "v3"
            ],
            96.417213
        ],
        [
            [
                "v3",
                "v2"
            ],
            96.755984
        ]
    ],
    "a1": [
        [
            "v13",
            0,
            49.086661210376406
        ],
        [
            [
                "v13",
                "v12"
            ],
            49.086661
        ],
        [
            "v12",
            50.30003407014691,
            51.02223354502529
        ],
        [
            [
                "v12",
                "v13"
            ],
            51.022234
        ],
        [
            "v13",
            52.235607070146905,
            94.18589052103438
        ],
        [
            [
                "v13",
                "v12"
            ],
            94.185891
        ],
        [
            "v12",
            95.3992640701469,
            96.41721252103437
        ],
        [
            [
                "v12",
                "v7"
            ],
            96.417213
        ],
        [
            "v7",
            101.8780390263149,
            103.30135768853025
        ]
    ],
    "a2": [
        [
            "v1",
            0,
            69.1902355221704
        ],
        [
            [
                "v1",
                "v23"
            ],
            69.190236
        ],
        [
            [
                "v23",
                "v5"
            ],
            71.05389
        ],
        [
            "v5",
            75.61042813255537,
            94.18589052103438
        ],
        [
            [
                "v5",
                "v23"
            ],
            94.185891
        ],
        [
            [
                "v23",
                "v11"
            ],
            98.742429
        ],
        [
            "v11",
            100.23394978142392,
            103.30135768853025
        ]
    ],
    "a0": [
        [
            "v14",
            0,
            11.509031461210956
        ],
        [
            [
                "v14",
                "v0"
            ],
            11.509031
        ],
        [
            [
                "v0",
                "v6"
            ],
            13.136547
        ],
        [
            [
                "v6",
                "v24"
            ],
            14.740582
        ],
        [
            "v24",
            19.03641810092483,
            43.186789886009095
        ],
        [
            [
                "v24",
                "v6"
            ],
            43.18679
        ],
        [
            [
                "v6",
                "v0"
            ],
            47.482626
        ],
        [
            "v0",
            49.086661210376406,
            75.61042813255537
        ],
        [
            [
                "v0",
                "v14"
            ],
            75.610428
        ],
        [
            "v14",
            77.23794401444536,
            103.30135768853025
        ]
    ],
    "a3": [
        [
            "v21",
            0,
            6.601108995924587
        ],
        [
            [
                "v21",
                "v2"
            ],
            6.601109
        ],
        [
            [
                "v2",
                "v3"
            ],
            11.509031
        ],
        [
            "v3",
            18.054404688530248,
            39.240744974531964
        ],
        [
            [
                "v3",
                "v8"
            ],
            39.240745
        ],
        [
            [
                "v8",
                "v4"
            ],
            39.579516
        ],
        [
            "v4",
            42.0036453166984,
            63.47548395889164
        ],
        [
            [
                "v4",
                "v22"
            ],
            63.475484
        ],
        [
            [
                "v22",
                "v24"
            ],
            66.584543
        ],
        [
            "v24",
            69.1902355221704,
            103.30135768853025
        ]
    ]
}